{"nodes": [{"id": "docs_architecture_system_overview", "label": "RustyLox Architecture Overview", "file_type": "document", "source_file": "docs/architecture.md", "source_location": "line 1", "source_url": null, "captured_at": null, "author": null, "contributor": null}, {"id": "concept_htmx_progressive_enhancement", "label": "HTMX Progressive Enhancement Pattern", "file_type": "rationale", "source_file": "docs/architecture.md", "source_location": "line 84", "source_url": null, "captured_at": null, "author": null, "contributor": null}, {"id": "concept_plugin_lifecycle_hooks", "label": "Plugin Lifecycle Hook System", "file_type": "concept", "source_file": "docs/architecture.md", "source_location": "line 47", "source_url": null, "captured_at": null, "author": null, "contributor": null}, {"id": "concept_atomic_json_writes", "label": "Atomic JSON File Write Pattern (temp-then-rename)", "file_type": "rationale", "source_file": "docs/architecture.md", "source_location": "line 98", "source_url": null, "captured_at": null, "author": null, "contributor": null}, {"id": "concept_cargo_workspace", "label": "Cargo Workspace Multi-Crate Architecture", "file_type": "rationale", "source_file": "docs/architecture.md", "source_location": "line 12", "source_url": null, "captured_at": null, "author": null, "contributor": null}, {"id": "concept_docker_multi_stage_build", "label": "Docker Multi-Stage Build Strategy", "file_type": "rationale", "source_file": "docs/architecture.md", "source_location": "line 93", "source_url": null, "captured_at": null, "author": null, "contributor": null}], "edges": [{"source": "docs_architecture_system_overview", "target": "concept_atomic_json_writes", "relation": "references", "confidence": "EXTRACTED", "confidence_score": 1.0, "source_file": "docs/architecture.md", "source_location": "line 98", "weight": 1.0}, {"source": "docs_architecture_system_overview", "target": "concept_cargo_workspace", "relation": "references", "confidence": "EXTRACTED", "confidence_score": 1.0, "source_file": "docs/architecture.md", "source_location": "line 12", "weight": 1.0}, {"source": "docs_architecture_system_overview", "target": "concept_htmx_progressive_enhancement", "relation": "references", "confidence": "EXTRACTED", "confidence_score": 1.0, "source_file": "docs/architecture.md", "source_location": "line 84", "weight": 1.0}, {"source": "docs_architecture_system_overview", "target": "concept_docker_multi_stage_build", "relation": "references", "confidence": "EXTRACTED", "confidence_score": 1.0, "source_file": "docs/architecture.md", "source_location": "line 93", "weight": 1.0}, {"source": "docs_architecture_system_overview", "target": "concept_plugin_lifecycle_hooks", "relation": "references", "confidence": "EXTRACTED", "confidence_score": 1.0, "source_file": "docs/architecture.md", "source_location": "line 47", "weight": 1.0}, {"source": "docs_architecture_system_overview", "target": "docs_api_rest_api_reference", "relation": "references", "confidence": "INFERRED", "confidence_score": 0.85, "source_file": "docs/architecture.md", "source_location": "line 39", "weight": 1.0}], "hyperedges": []}